{

  "bUseAppLoginType": false,
  "LoginType": 0,

  "bUseLogLevel": true,

  "bShowAdminInfo": false,

  "bUseLanguageSet": false,

  "bUseMainPageType": true,

  "bUseStartProgramReg": true,

  "bManualDownFolderChange": false,
  "bManualRecvDownChange": false,

  "bRFileAutoSend": false,
  "bRMouseFileAddAfterTrans": false,

  "bShowAfterApprAutoCheck": true,
  "bAfterBasicChk": false,

  "bFileRecvAlarmRetain": false,
  "bFileRecvTrayFix": false,
  "bApprCompleteAlarmRetain": false,
  "bUserApprActionTrayFix": false,
  "bApprRejectAlarmRetain": false,
  "bUserApprRejectTrayFix": false,
  "bApprCountAlarmRetain": false,
  "bApprTrayFix": true,
  "bUseApprCountAlaram": false,
  "bUseApprWaitNoti": true,


  "bUserIDSave": false,
  "bAutoLogin": false,
  "bAutoLoginCheck": true,
  "bUserPWChange": false,


  "bDeputyApprTerminateDel": false,
  "bDlpInfoDisplay": false,
  "bEmptyfileTrans": true,

  "strInitPasswd": "1K27SdexltsW0ubSCJgsZw==",
  "strPWChangeProhibitLimit": "",
  "nPWChangeApplyCnt": 9,

  "bURLAutoTrans": [
    true,
    false,
    false
  ],
  "strURLAutoAfterBrowser": [
    "N",
    "N",
    "F"
  ],
  "bURLAutoAfterMsg": [
    true,
    true,
    true
  ],
  "strForwardUrl": [
    "http:\/\/naver.com",
    "http:\/\/daum.net",
    "http:\/\/daum.net"
  ],

  "bUseClipBoardFileTrans": true,
  "bUseFileClipManageUI": true,
  "bUseFileClipApproveUI": true,

  "bScreenLockUserChange": true,
  "bScreenLock": false,

  "enMainPageType": 0,
  "bNoApproveManageUI": false,
  "bRecvDownPathChange": true,
  "bStartProgramReg": true,
  "bTitleDescSameChk": false,

  "bUseFileCheckException": false,
  "bUseNetOverAllsend": false,
  "listUseGpkiLogin": [
    false,
    false,
    false
  ],
  "bClipBoardNoApproveButFileTrans": true,
  "bUseDenyPasswordZip": true,
  "bRecvFolderChange": false,
  "bURLListPolicyRecv": false,
  "bUseCertSend": false,
  "blistUseEmail": [
    false,
    false
  ],
  "bUseForceUpdate": true,
  "bUsePCURL": false,
  "bUsePublicBoard": false,
  "bUseUserRecvDownPath": true,
  "bUseUserRecvDownPathUserName": true,
  "bUseUserSelectFirstServer": false,
  "bViewDlpApproverSelectMyDept": false,
  "bViewFileFilter": true,
  "bViewSGHeaderUIAlarmNoriAllDel": true,
  "bViewSGSideBarUIBadge": false,
  "nClipAfterApproveUseType": 2,
  "bUseOneToMultiLogin": false,
  "bUseOneByOneLogOut" : false,
  "bApprDeptSearch": true,
  "bApprLineChkBlock": false,
  "bApprLineLocalSave": true,

  "nApprStepLimit": 0,

  "bUseClipAlarmType": true,
  "bUseClipCopyAndSend": false,
  "bClipCopyAutoSend": false,

  "bUseCloseTrayMove": false,
  "bExitTrayMove": false,

  "bUseStartTrayMove": false,
  "bStartTrayMove": false,

  "bUseFileForward": true,
  "bFileDownloadBeforeReciving": false,

  "bRecvFolderOpen": false,
  "bUseAgentTime1aClock": false,

  "bUsePartialFileAddInTransfer" : false

  

}